{
  "title": "DSC_0131.NEF",
  "description": "",
  "imageViews": "0",
  "creationTime": {
    "timestamp": "1565494709",
    "formatted": "Aug 11, 2019, 3:38:29 AM UTC"
  },
  "modificationTime": {
    "timestamp": "1577820437",
    "formatted": "Dec 31, 2019, 7:27:17 PM UTC"
  },
  "geoData": {
    "latitude": 0.0,
    "longitude": 0.0,
    "altitude": 0.0,
    "latitudeSpan": 0.0,
    "longitudeSpan": 0.0
  },
  "geoDataExif": {
    "latitude": 0.0,
    "longitude": 0.0,
    "altitude": 0.0,
    "latitudeSpan": 0.0,
    "longitudeSpan": 0.0
  },
  "photoTakenTime": {
    "timestamp": "1237746030",
    "formatted": "Mar 22, 2009, 6:20:30 PM UTC"
  }
}