{
  "title": "DSC01104.JPG",
  "description": "",
  "imageViews": "0",
  "creationTime": {
    "timestamp": "1562367167",
    "formatted": "Jul 5, 2019, 10:52:47 PM UTC"
  },
  "modificationTime": {
    "timestamp": "1577820250",
    "formatted": "Dec 31, 2019, 7:24:10 PM UTC"
  },
  "geoData": {
    "latitude": 0.0,
    "longitude": 0.0,
    "altitude": 0.0,
    "latitudeSpan": 0.0,
    "longitudeSpan": 0.0
  },
  "geoDataExif": {
    "latitude": 0.0,
    "longitude": 0.0,
    "altitude": 0.0,
    "latitudeSpan": 0.0,
    "longitudeSpan": 0.0
  },
  "photoTakenTime": {
    "timestamp": "1116205908",
    "formatted": "May 16, 2005, 1:11:48 AM UTC"
  }
}