{
  "title": "IMGP0186.JPG",
  "description": "",
  "imageViews": "0",
  "creationTime": {
    "timestamp": "1562368915",
    "formatted": "Jul 5, 2019, 11:21:55 PM UTC"
  },
  "modificationTime": {
    "timestamp": "1584970421",
    "formatted": "Mar 23, 2020, 1:33:41 PM UTC"
  },
  "geoData": {
    "latitude": 0.0,
    "longitude": 0.0,
    "altitude": 0.0,
    "latitudeSpan": 0.0,
    "longitudeSpan": 0.0
  },
  "geoDataExif": {
    "latitude": 0.0,
    "longitude": 0.0,
    "altitude": 0.0,
    "latitudeSpan": 0.0,
    "longitudeSpan": 0.0
  },
  "photoTakenTime": {
    "timestamp": "1123124400",
    "formatted": "Aug 4, 2005, 3:00:00 AM UTC"
  }
}