{
  "title": "IMGP1058.JPG",
  "description": "",
  "imageViews": "0",
  "creationTime": {
    "timestamp": "1562437182",
    "formatted": "Jul 6, 2019, 6:19:42 PM UTC"
  },
  "modificationTime": {
    "timestamp": "1579776329",
    "formatted": "Jan 23, 2020, 10:45:29 AM UTC"
  },
  "geoData": {
    "latitude": 0.0,
    "longitude": 0.0,
    "altitude": 0.0,
    "latitudeSpan": 0.0,
    "longitudeSpan": 0.0
  },
  "geoDataExif": {
    "latitude": 0.0,
    "longitude": 0.0,
    "altitude": 0.0,
    "latitudeSpan": 0.0,
    "longitudeSpan": 0.0
  },
  "photoTakenTime": {
    "timestamp": "1143260977",
    "formatted": "Mar 25, 2006, 4:29:37 AM UTC"
  }
}