{
  "title": "Kids July2003 009.jpg",
  "description": "",
  "imageViews": "0",
  "creationTime": {
    "timestamp": "1562360618",
    "formatted": "Jul 5, 2019, 9:03:38 PM UTC"
  },
  "modificationTime": {
    "timestamp": "1579776321",
    "formatted": "Jan 23, 2020, 10:45:21 AM UTC"
  },
  "geoData": {
    "latitude": 0.0,
    "longitude": 0.0,
    "altitude": 0.0,
    "latitudeSpan": 0.0,
    "longitudeSpan": 0.0
  },
  "geoDataExif": {
    "latitude": 0.0,
    "longitude": 0.0,
    "altitude": 0.0,
    "latitudeSpan": 0.0,
    "longitudeSpan": 0.0
  },
  "photoTakenTime": {
    "timestamp": "1057890546",
    "formatted": "Jul 11, 2003, 2:29:06 AM UTC"
  }
}