{
  "title": "DSC00822.JPG",
  "description": "",
  "imageViews": "0",
  "creationTime": {
    "timestamp": "1562364895",
    "formatted": "Jul 5, 2019, 10:14:55 PM UTC"
  },
  "modificationTime": {
    "timestamp": "1584765382",
    "formatted": "Mar 21, 2020, 4:36:22 AM UTC"
  },
  "geoData": {
    "latitude": 0.0,
    "longitude": 0.0,
    "altitude": 0.0,
    "latitudeSpan": 0.0,
    "longitudeSpan": 0.0
  },
  "geoDataExif": {
    "latitude": 0.0,
    "longitude": 0.0,
    "altitude": 0.0,
    "latitudeSpan": 0.0,
    "longitudeSpan": 0.0
  },
  "photoTakenTime": {
    "timestamp": "1102800409",
    "formatted": "Dec 11, 2004, 9:26:49 PM UTC"
  }
}