{
  "title": "IMG_0202.JPG",
  "description": "",
  "imageViews": "0",
  "creationTime": {
    "timestamp": "1565569359",
    "formatted": "Aug 12, 2019, 12:22:39 AM UTC"
  },
  "modificationTime": {
    "timestamp": "1579776365",
    "formatted": "Jan 23, 2020, 10:46:05 AM UTC"
  },
  "geoData": {
    "latitude": 37.803333333333335,
    "longitude": -122.402,
    "altitude": 66.94412607449857,
    "latitudeSpan": 0.0,
    "longitudeSpan": 0.0
  },
  "geoDataExif": {
    "latitude": 37.803333333333335,
    "longitude": -122.402,
    "altitude": 66.94412607449857,
    "latitudeSpan": 0.0,
    "longitudeSpan": 0.0
  },
  "photoTakenTime": {
    "timestamp": "1288204495",
    "formatted": "Oct 27, 2010, 6:34:55 PM UTC"
  }
}