{
  "title": "IMG_0744.JPG",
  "description": "",
  "imageViews": "0",
  "creationTime": {
    "timestamp": "1586116259",
    "formatted": "Apr 5, 2020, 7:50:59 PM UTC"
  },
  "modificationTime": {
    "timestamp": "1586116959",
    "formatted": "Apr 5, 2020, 8:02:39 PM UTC"
  },
  "geoData": {
    "latitude": 37.91713333333333,
    "longitude": -122.49491111111111,
    "altitude": 120.34943181818181,
    "latitudeSpan": 0.0,
    "longitudeSpan": 0.0
  },
  "geoDataExif": {
    "latitude": 37.91713333333333,
    "longitude": -122.49491111111111,
    "altitude": 120.34943181818181,
    "latitudeSpan": 0.0,
    "longitudeSpan": 0.0
  },
  "photoTakenTime": {
    "timestamp": "1527459710",
    "formatted": "May 27, 2018, 10:21:50 PM UTC"
  }
}