{
  "title": "IMG_0327.JPG",
  "description": "",
  "imageViews": "0",
  "creationTime": {
    "timestamp": "1586115816",
    "formatted": "Apr 5, 2020, 7:43:36 PM UTC"
  },
  "modificationTime": {
    "timestamp": "1586116712",
    "formatted": "Apr 5, 2020, 7:58:32 PM UTC"
  },
  "geoData": {
    "latitude": 37.792538888888885,
    "longitude": -122.40165,
    "altitude": 9.965564727754018,
    "latitudeSpan": 0.0,
    "longitudeSpan": 0.0
  },
  "geoDataExif": {
    "latitude": 37.792538888888885,
    "longitude": -122.40165,
    "altitude": 9.965564727754018,
    "latitudeSpan": 0.0,
    "longitudeSpan": 0.0
  },
  "photoTakenTime": {
    "timestamp": "1544464701",
    "formatted": "Dec 10, 2018, 5:58:21 PM UTC"
  }
}