{
  "title": "IMG_1326.JPG",
  "description": "",
  "imageViews": "0",
  "creationTime": {
    "timestamp": "1586113681",
    "formatted": "Apr 5, 2020, 7:08:01 PM UTC"
  },
  "modificationTime": {
    "timestamp": "1586114209",
    "formatted": "Apr 5, 2020, 7:16:49 PM UTC"
  },
  "geoData": {
    "latitude": 37.91565833333333,
    "longitude": -122.50824722222222,
    "altitude": 5.348663327925514,
    "latitudeSpan": 0.0,
    "longitudeSpan": 0.0
  },
  "geoDataExif": {
    "latitude": 37.91565833333333,
    "longitude": -122.50824722222222,
    "altitude": 5.348663327925514,
    "latitudeSpan": 0.0,
    "longitudeSpan": 0.0
  },
  "photoTakenTime": {
    "timestamp": "1572633356",
    "formatted": "Nov 1, 2019, 6:35:56 PM UTC"
  }
}