{
  "title": "Claire Playof 1_20081108_073.JPG",
  "description": "",
  "imageViews": "0",
  "creationTime": {
    "timestamp": "1565418024",
    "formatted": "Aug 10, 2019, 6:20:24 AM UTC"
  },
  "modificationTime": {
    "timestamp": "1577820428",
    "formatted": "Dec 31, 2019, 7:27:08 PM UTC"
  },
  "geoData": {
    "latitude": 0.0,
    "longitude": 0.0,
    "altitude": 0.0,
    "latitudeSpan": 0.0,
    "longitudeSpan": 0.0
  },
  "geoDataExif": {
    "latitude": 0.0,
    "longitude": 0.0,
    "altitude": 0.0,
    "latitudeSpan": 0.0,
    "longitudeSpan": 0.0
  },
  "photoTakenTime": {
    "timestamp": "1226172073",
    "formatted": "Nov 8, 2008, 7:21:13 PM UTC"
  }
}