{
  "title": "IMG_0133.JPG",
  "description": "",
  "imageViews": "0",
  "creationTime": {
    "timestamp": "1565459255",
    "formatted": "Aug 10, 2019, 5:47:35 PM UTC"
  },
  "modificationTime": {
    "timestamp": "1577820432",
    "formatted": "Dec 31, 2019, 7:27:12 PM UTC"
  },
  "geoData": {
    "latitude": 38.0255,
    "longitude": -122.55533333333334,
    "altitude": 0.0,
    "latitudeSpan": 0.0,
    "longitudeSpan": 0.0
  },
  "geoDataExif": {
    "latitude": 38.0255,
    "longitude": -122.55533333333334,
    "altitude": 0.0,
    "latitudeSpan": 0.0,
    "longitudeSpan": 0.0
  },
  "photoTakenTime": {
    "timestamp": "1229909705",
    "formatted": "Dec 22, 2008, 1:35:05 AM UTC"
  }
}