{
  "title": "DSC_0074.JPG",
  "description": "",
  "imageViews": "0",
  "creationTime": {
    "timestamp": "1562457719",
    "formatted": "Jul 7, 2019, 12:01:59 AM UTC"
  },
  "modificationTime": {
    "timestamp": "1577820327",
    "formatted": "Dec 31, 2019, 7:25:27 PM UTC"
  },
  "geoData": {
    "latitude": 0.0,
    "longitude": 0.0,
    "altitude": 0.0,
    "latitudeSpan": 0.0,
    "longitudeSpan": 0.0
  },
  "geoDataExif": {
    "latitude": 0.0,
    "longitude": 0.0,
    "altitude": 0.0,
    "latitudeSpan": 0.0,
    "longitudeSpan": 0.0
  },
  "photoTakenTime": {
    "timestamp": "1194108803",
    "formatted": "Nov 3, 2007, 4:53:23 PM UTC"
  }
}