{
  "title": "DSC_0178.JPG",
  "description": "",
  "imageViews": "0",
  "creationTime": {
    "timestamp": "1562450816",
    "formatted": "Jul 6, 2019, 10:06:56 PM UTC"
  },
  "modificationTime": {
    "timestamp": "1577820313",
    "formatted": "Dec 31, 2019, 7:25:13 PM UTC"
  },
  "geoData": {
    "latitude": 0.0,
    "longitude": 0.0,
    "altitude": 0.0,
    "latitudeSpan": 0.0,
    "longitudeSpan": 0.0
  },
  "geoDataExif": {
    "latitude": 0.0,
    "longitude": 0.0,
    "altitude": 0.0,
    "latitudeSpan": 0.0,
    "longitudeSpan": 0.0
  },
  "photoTakenTime": {
    "timestamp": "1186795705",
    "formatted": "Aug 11, 2007, 1:28:25 AM UTC"
  }
}